gibica/__init__.py
gibica/ast.py
gibica/builtins.py
gibica/entrypoint.py
gibica/exceptions.py
gibica/interpreter.py
gibica/lexer.py
gibica/memory.py
gibica/parser.py
gibica/sementic.py
gibica/tokens.py
gibica/types.py
gibica-0.8.2.dist-info/AUTHORS
gibica-0.8.2.dist-info/LICENSE
gibica-0.8.2.dist-info/METADATA
gibica-0.8.2.dist-info/WHEEL
gibica-0.8.2.dist-info/entry_points.txt
gibica-0.8.2.dist-info/top_level.txt
gibica-0.8.2.dist-info/RECORD
