Metadata-Version: 2.1
Name: gibica
Version: 0.8.2
Summary: Interprète ? Interprète ? Cuillère !
Home-page: https://github.com/matthieugouel/gibica
Author: Matthieu Gouel
Author-email: matthieu.gouel@gmail.com
License: MIT
Platform: UNKNOWN
Classifier: Development Status :: 3 - Alpha
Classifier: Programming Language :: Python
Classifier: Programming Language :: Python :: 3
Classifier: Programming Language :: Python :: 3.6
Classifier: Programming Language :: Python :: 3.7
Classifier: Operating System :: OS Independent
Classifier: Environment :: Console
Classifier: Intended Audience :: Developers
Classifier: License :: OSI Approved :: MIT License
Requires-Python: >=3.6
Requires-Dist: click
